planets_yapr/__init__.py
planets_yapr/wrapper.py
planets_yapr/__pyinstaller/__init__.py
planets_yapr/__pyinstaller/hook-planets_yapr.py
planets_yapr/yapr/ICSharpCode.SharpZipLib.dll
planets_yapr/yapr/Microsoft.Win32.SystemEvents.dll
planets_yapr/yapr/PropertyChanged.dll
planets_yapr/yapr/SixLabors.ImageSharp.dll
planets_yapr/yapr/System.Drawing.Common.dll
planets_yapr/yapr/UndertaleModLib.dll
planets_yapr/yapr/UndertaleModLib.xml
planets_yapr/yapr/YAPR-LIB.deps.json
planets_yapr/yapr/YAPR-LIB.dll
planets_yapr/yapr/YAPR-LIB.pdb
planets_yapr/yapr/Sprites/Planets/spr_ITEM_Big_Missile/spr_ITEM_Big_Missile_0.png
planets_yapr/yapr/Sprites/Planets/spr_ITEM_Big_Missile/spr_ITEM_Big_Missile_1.png
planets_yapr/yapr/Sprites/Planets/spr_ITEM_Big_Missile/spr_ITEM_Big_Missile_2.png
planets_yapr/yapr/Sprites/Planets/spr_ITEM_Big_Missile/spr_ITEM_Big_Missile_3.png
planets_yapr/yapr/Sprites/Planets/spr_ITEM_Tourian_Key/spr_ITEM_Tourian_Key_0.png
planets_yapr/yapr/Sprites/Planets/spr_ITEM_Tourian_Key/spr_ITEM_Tourian_Key_1.png
planets_yapr/yapr/runtimes/unix/lib/netcoreapp3.0/System.Drawing.Common.dll
planets_yapr/yapr/runtimes/win/lib/netcoreapp3.0/Microsoft.Win32.SystemEvents.dll
planets_yapr/yapr/runtimes/win/lib/netcoreapp3.0/System.Drawing.Common.dll
planets_yapr-1.0.1.dist-info/licenses/LICENSE
planets_yapr-1.0.1.dist-info/METADATA
planets_yapr-1.0.1.dist-info/WHEEL
planets_yapr-1.0.1.dist-info/entry_points.txt
planets_yapr-1.0.1.dist-info/top_level.txt
planets_yapr-1.0.1.dist-info/RECORD
