Metadata-Version: 2.4
Name: planets-yapr
Version: 1.0.1
Summary: An open source randomizer patcher for Metroid Planets.
Author: UltiNaruto
License:                     GNU GENERAL PUBLIC LICENSE
Project-URL: Repository, https://github.com/UltiNaruto/YAPR
Classifier: Programming Language :: Python :: 3
Classifier: License :: OSI Approved :: GNU General Public License v3 (GPLv3)
Classifier: Development Status :: 3 - Alpha
Classifier: Programming Language :: Python :: 3.11
Requires-Python: >=3.11
License-File: LICENSE
Requires-Dist: pythonnet
Provides-Extra: test
Requires-Dist: pytest; extra == "test"
Requires-Dist: pytest-cov; extra == "test"
Requires-Dist: pytest-mock; extra == "test"
Dynamic: license-file
